Workbook

Sheet Assumptions
A1: JURY INCENTIVE MODEL: ASSUMPTIONS
A3: PLATFORM GROWTH
A4: Jobs per month (baseline) | B4: 1000
A5: Jobs per month (Year 2) | B5: 2500
A6: Jobs per month (Year 3) | B6: 5000
A7: Dispute rate (%) | B7: 5
A8: Avg escrow per job ($) | B8: 1000
A10: JURY ECONOMICS
A11: Avg jurors per case | B11: 3
A12: Certified tier (% of jury pool) | B12: 60
A13: Senior tier (% of jury pool) | B13: 25
A14: Arbitrum tier (% of jury pool) | B14: 15
A15: Consensus rate (%) | B15: 75
A16: Appeal rate (%) | B16: 4
A17: Appeal overturn rate (%) | B17: 3
A19: JUROR FEES BY TIER
A20: Tier | B20: Base Fee ($) | C20: Escrow % (mid-range) | D20: Avg Case ($)
A21: Certified | B21: 10 | C21: 0.015 | D21: 1000
A22: Senior | B22: 20 | C22: 0.0175 | D22: 2500
A23: Arbitrum | B23: 30 | C23: 0.02 | D23: 5000
A25: REVENUE ALLOCATION
A26: Loser pays juror fees (%) | B26: 100
A27: Appeal fund (% of escrow) | B27: 2
A28: HP protocol fee (% of escrow) | B28: 1
A29: HP share of appeal fund (%) | B29: 50
A30: Juror consensus bonus (%) | B30: 50

Sheet Monthly P&L
A1: JURY SYSTEM: MONTHLY P&L
A3: Month | B3: Jobs Posted | C3: Total Escrow | D3: Disputes (#) | E3: Cases to Jury | F3: Juror Assignments | G3: Juror Fees (Paid) | H3: Appeal Fund (2%) | I3: HP Protocol (1%) | J3: Appeals Filed | K3: Appeals Granted | L3: HP Appeal Revenue | M3: HP Total Revenue | N3: Net Monthly Cost
A4: Month 1 | B4: =Assumptions!$B$3 -> 0 | C4: =B4*Assumptions!$B$7 -> 0 | D4: =B4*Assumptions!$B$6 -> 0 | E4: =D4 -> 0 | F4: =E4*Assumptions!$B$18 -> 0 | G4: =F4*20 -> 0 | H4: =C4*Assumptions!$B$28 -> 0 | I4: =C4*Assumptions!$B$29 -> 0 | J4: =E4*Assumptions!$B$21 -> 0 | K4: =J4*Assumptions!$B$22 -> 0 | L4: =H4*Assumptions!$B$30*(J4/MAX(E4,1)) -> 0 | M4: =I4+L4 -> 0 | N4: =G4-M4 -> 0
A5: Month 2 | B5: =Assumptions!$B$3 -> 0 | C5: =B5*Assumptions!$B$7 -> 0 | D5: =B5*Assumptions!$B$6 -> 0 | E5: =D5 -> 0 | F5: =E5*Assumptions!$B$18 -> 0 | G5: =F5*20 -> 0 | H5: =C5*Assumptions!$B$28 -> 0 | I5: =C5*Assumptions!$B$29 -> 0 | J5: =E5*Assumptions!$B$21 -> 0 | K5: =J5*Assumptions!$B$22 -> 0 | L5: =H5*Assumptions!$B$30*(J5/MAX(E5,1)) -> 0 | M5: =I5+L5 -> 0 | N5: =G5-M5 -> 0
A6: Month 3 | B6: =Assumptions!$B$3 -> 0 | C6: =B6*Assumptions!$B$7 -> 0 | D6: =B6*Assumptions!$B$6 -> 0 | E6: =D6 -> 0 | F6: =E6*Assumptions!$B$18 -> 0 | G6: =F6*20 -> 0 | H6: =C6*Assumptions!$B$28 -> 0 | I6: =C6*Assumptions!$B$29 -> 0 | J6: =E6*Assumptions!$B$21 -> 0 | K6: =J6*Assumptions!$B$22 -> 0 | L6: =H6*Assumptions!$B$30*(J6/MAX(E6,1)) -> 0 | M6: =I6+L6 -> 0 | N6: =G6-M6 -> 0
A7: Month 4 | B7: =Assumptions!$B$3 -> 0 | C7: =B7*Assumptions!$B$7 -> 0 | D7: =B7*Assumptions!$B$6 -> 0 | E7: =D7 -> 0 | F7: =E7*Assumptions!$B$18 -> 0 | G7: =F7*20 -> 0 | H7: =C7*Assumptions!$B$28 -> 0 | I7: =C7*Assumptions!$B$29 -> 0 | J7: =E7*Assumptions!$B$21 -> 0 | K7: =J7*Assumptions!$B$22 -> 0 | L7: =H7*Assumptions!$B$30*(J7/MAX(E7,1)) -> 0 | M7: =I7+L7 -> 0 | N7: =G7-M7 -> 0
A8: Month 5 | B8: =Assumptions!$B$3 -> 0 | C8: =B8*Assumptions!$B$7 -> 0 | D8: =B8*Assumptions!$B$6 -> 0 | E8: =D8 -> 0 | F8: =E8*Assumptions!$B$18 -> 0 | G8: =F8*20 -> 0 | H8: =C8*Assumptions!$B$28 -> 0 | I8: =C8*Assumptions!$B$29 -> 0 | J8: =E8*Assumptions!$B$21 -> 0 | K8: =J8*Assumptions!$B$22 -> 0 | L8: =H8*Assumptions!$B$30*(J8/MAX(E8,1)) -> 0 | M8: =I8+L8 -> 0 | N8: =G8-M8 -> 0
A9: Month 6 | B9: =Assumptions!$B$3 -> 0 | C9: =B9*Assumptions!$B$7 -> 0 | D9: =B9*Assumptions!$B$6 -> 0 | E9: =D9 -> 0 | F9: =E9*Assumptions!$B$18 -> 0 | G9: =F9*20 -> 0 | H9: =C9*Assumptions!$B$28 -> 0 | I9: =C9*Assumptions!$B$29 -> 0 | J9: =E9*Assumptions!$B$21 -> 0 | K9: =J9*Assumptions!$B$22 -> 0 | L9: =H9*Assumptions!$B$30*(J9/MAX(E9,1)) -> 0 | M9: =I9+L9 -> 0 | N9: =G9-M9 -> 0
A10: Month 7 | B10: =Assumptions!$B$3 -> 0 | C10: =B10*Assumptions!$B$7 -> 0 | D10: =B10*Assumptions!$B$6 -> 0 | E10: =D10 -> 0 | F10: =E10*Assumptions!$B$18 -> 0 | G10: =F10*20 -> 0 | H10: =C10*Assumptions!$B$28 -> 0 | I10: =C10*Assumptions!$B$29 -> 0 | J10: =E10*Assumptions!$B$21 -> 0 | K10: =J10*Assumptions!$B$22 -> 0 | L10: =H10*Assumptions!$B$30*(J10/MAX(E10,1)) -> 0 | M10: =I10+L10 -> 0 | N10: =G10-M10 -> 0
A11: Month 8 | B11: =Assumptions!$B$3 -> 0 | C11: =B11*Assumptions!$B$7 -> 0 | D11: =B11*Assumptions!$B$6 -> 0 | E11: =D11 -> 0 | F11: =E11*Assumptions!$B$18 -> 0 | G11: =F11*20 -> 0 | H11: =C11*Assumptions!$B$28 -> 0 | I11: =C11*Assumptions!$B$29 -> 0 | J11: =E11*Assumptions!$B$21 -> 0 | K11: =J11*Assumptions!$B$22 -> 0 | L11: =H11*Assumptions!$B$30*(J11/MAX(E11,1)) -> 0 | M11: =I11+L11 -> 0 | N11: =G11-M11 -> 0
A12: Month 9 | B12: =Assumptions!$B$3 -> 0 | C12: =B12*Assumptions!$B$7 -> 0 | D12: =B12*Assumptions!$B$6 -> 0 | E12: =D12 -> 0 | F12: =E12*Assumptions!$B$18 -> 0 | G12: =F12*20 -> 0 | H12: =C12*Assumptions!$B$28 -> 0 | I12: =C12*Assumptions!$B$29 -> 0 | J12: =E12*Assumptions!$B$21 -> 0 | K12: =J12*Assumptions!$B$22 -> 0 | L12: =H12*Assumptions!$B$30*(J12/MAX(E12,1)) -> 0 | M12: =I12+L12 -> 0 | N12: =G12-M12 -> 0
A13: Month 10 | B13: =Assumptions!$B$3 -> 0 | C13: =B13*Assumptions!$B$7 -> 0 | D13: =B13*Assumptions!$B$6 -> 0 | E13: =D13 -> 0 | F13: =E13*Assumptions!$B$18 -> 0 | G13: =F13*20 -> 0 | H13: =C13*Assumptions!$B$28 -> 0 | I13: =C13*Assumptions!$B$29 -> 0 | J13: =E13*Assumptions!$B$21 -> 0 | K13: =J13*Assumptions!$B$22 -> 0 | L13: =H13*Assumptions!$B$30*(J13/MAX(E13,1)) -> 0 | M13: =I13+L13 -> 0 | N13: =G13-M13 -> 0
A14: Month 11 | B14: =Assumptions!$B$3 -> 0 | C14: =B14*Assumptions!$B$7 -> 0 | D14: =B14*Assumptions!$B$6 -> 0 | E14: =D14 -> 0 | F14: =E14*Assumptions!$B$18 -> 0 | G14: =F14*20 -> 0 | H14: =C14*Assumptions!$B$28 -> 0 | I14: =C14*Assumptions!$B$29 -> 0 | J14: =E14*Assumptions!$B$21 -> 0 | K14: =J14*Assumptions!$B$22 -> 0 | L14: =H14*Assumptions!$B$30*(J14/MAX(E14,1)) -> 0 | M14: =I14+L14 -> 0 | N14: =G14-M14 -> 0
A15: Month 12 | B15: =Assumptions!$B$3 -> 0 | C15: =B15*Assumptions!$B$7 -> 0 | D15: =B15*Assumptions!$B$6 -> 0 | E15: =D15 -> 0 | F15: =E15*Assumptions!$B$18 -> 0 | G15: =F15*20 -> 0 | H15: =C15*Assumptions!$B$28 -> 0 | I15: =C15*Assumptions!$B$29 -> 0 | J15: =E15*Assumptions!$B$21 -> 0 | K15: =J15*Assumptions!$B$22 -> 0 | L15: =H15*Assumptions!$B$30*(J15/MAX(E15,1)) -> 0 | M15: =I15+L15 -> 0 | N15: =G15-M15 -> 0
B16: =SUM(B4:B15) -> 0 | C16: =SUM(C4:C15) -> 0 | D16: =SUM(D4:D15) -> 0 | E16: =SUM(E4:E15) -> 0 | F16: =SUM(F4:F15) -> 0 | G16: =SUM(G4:G15) -> 0 | H16: =SUM(H4:H15) -> 0 | I16: =SUM(I4:I15) -> 0 | ... N16: =SUM(N4:N15) -> 0
A17: YEAR 1 TOTALS | B17: =SUM(B5:B16) -> 0 | C17: =SUM(C5:C16) -> 0 | D17: =SUM(D5:D16) -> 0 | E17: =SUM(E5:E16) -> 0 | F17: =SUM(F5:F16) -> 0 | G17: =SUM(G5:G16) -> 0 | H17: =SUM(H5:H16) -> 0 | I17: =SUM(I5:I16) -> 0 | ... N17: =SUM(N5:N16) -> 0

Sheet Juror Earnings
A1: JUROR EARNING SCENARIOS (Annual)
A3: Tier | B3: Cases/Month | C3: Avg Case Escrow | D3: Base Fee per Case | E3: Consensus Bonus (50%) | F3: Annual Earnings
A4: Certified - Light | B4: 2 | C4: 1000 | D4: 10 | E4: =(10+1000*0.015)*1.35 -> 33.75 | F4: =(10+1000*0.015)*2*12*1.35 -> 810
A5: Certified - Medium | B5: 4 | C5: 1000 | D5: 10 | E5: =(10+1000*0.015)*1.35 -> 33.75 | F5: =(10+1000*0.015)*4*12*1.35 -> 1620
A6: Certified - Heavy | B6: 6 | C6: 1000 | D6: 10 | E6: =(10+1000*0.015)*1.35 -> 33.75 | F6: =(10+1000*0.015)*6*12*1.35 -> 2430
A7: Senior - Light | B7: 2 | C7: 2500 | D7: 20 | E7: =(20+2500*0.0175)*1.35 -> 86.0625 | F7: =(20+2500*0.0175)*2*12*1.35 -> 2065.5
A8: Senior - Medium | B8: 4 | C8: 2500 | D8: 20 | E8: =(20+2500*0.0175)*1.35 -> 86.0625 | F8: =(20+2500*0.0175)*4*12*1.35 -> 4131
A9: Arbitrum - Medium | B9: 3 | C9: 5000 | D9: 30 | E9: =(30+5000*0.02)*1.35 -> 175.5 | F9: =(30+5000*0.02)*3*12*1.35 -> 6318
A12: JURY KARMA VALUATION
A13: Jury Karma points earned per case | B13: 50
A14: Estimated platform value per JK point | B14: 0.02
A15: Annual JK earned (at 48 cases/year) | B15: =50*48 -> 2400
A16: Imputed annual value from JK | B16: =B15*B13 -> 120000

Sheet Pool Growth
A1: JURY POOL GROWTH PROJECTION (3 YEARS)
A3: Year | B3: Jobs/Month | C3: Disputes/Month | D3: Jury Assignments/Mo | E3: Pool Size (Certified+) | F3: Utilization Rate | G3: Avg Cases/Juror
A4: Year 1 | B4: =Assumptions!B3 -> 0 | C4: =B5*Assumptions!B6 -> 5000000 | D4: =C5*Assumptions!B18 -> 0 | E4: 100 | F4: =D5/(E5/4) -> 0 | G4: =D5/E5 -> 0
A5: Year 2 | B5: =Assumptions!B4 -> 1000 | C5: =B6*Assumptions!B6 -> 12500000 | D5: =C6*Assumptions!B18 -> 0 | E5: 200 | F5: =IF(E5>0, D5/(E5/4), 0) -> 0 | G5: =IF(E5>0, D5/E5, 0) -> 0
A6: Year 3 | B6: =Assumptions!B5 -> 2500 | C6: =B7*Assumptions!B6 -> 0 | D6: =C7*Assumptions!B18 -> 0 | E6: 350 | F6: =IF(E6>0, D6/(E6/4), 0) -> 0 | G6: =IF(E6>0, D6/E6, 0) -> 0
F7: =IF(E7>0, D7/(E7/4), 0) -> 0 | G7: =IF(E7>0, D7/E7, 0) -> 0

Sheet Risk Mitigation
A1: JURY SYSTEM: RISK & MITIGATION
A3: RISK | B3: PROBABILITY | C3: ANNUAL IMPACT | D3: MITIGATION | E3: COST
A4: Collusion (2 agents split jury fee) | B4: Low (2%) | C4: $5,000 | D4: USDC flow monitoring + pattern detection | E4: $500
A5: Appeal spam (wealthy agents) | B5: Medium (5%) | C5: $10,000 | D5: Fee escalation + appeal rate limits | E5: $200
A6: Juror burnout (overload) | B6: Low (3%) | C6: $3,000 | D6: Case cap + sabbatical option | E6: Internal
A7: Tier gaming (dummy jobs) | B7: Low (1%) | C7: $2,000 | D7: Job density limits + analyst review | E7: Internal
A8: Juror consensus failure (all wrong) | B8: Very Low (1%) | C8: $1,000 | D8: Appeal mechanism + senior review | E8: $100

Sheet Success Metrics
A1: JURY SYSTEM: SUCCESS METRICS DASHBOARD
A3: METRIC | B3: BASELINE | C3: TARGET (YEAR 1) | D3: TARGET (YEAR 2) | E3: MONITORING
A4: Jury pool size | B4: 0 | C4: 100 | D4: 200 | E4: Weekly
A5: Verdict consensus rate (%) | B5: - | C5: 75% | D5: 80% | E5: Monthly
A6: Appeal rate (%) | B6: - | C6: 4% | D6: 3% | E6: Monthly
A7: Appeal overturn rate (%) | B7: - | C7: <5% | D7: <3% | E7: Monthly
A8: Juror retention (QoQ %) | B8: - | C8: 80% | D8: 85% | E8: Quarterly
A9: Avg juror earnings/case ($) | B9: - | C9: $25 | D9: $30 | E9: Monthly
A10: Client satisfaction (%) | B10: - | C10: 85% | D10: 90% | E10: Per case
A11: Worker satisfaction (%) | B11: - | C11: 85% | D11: 90% | E11: Per case
A12: Time to verdict (hours) | B12: - | C12: 48 | D12: 36 | E12: Per case
A13: HP revenue per dispute ($) | B13: - | C13: $10 | D13: $12 | E13: Monthly
